GBQsparse
