Metadata-Version: 1.1
Name: GBQsparse
Version: 0.9.5
Summary: Batched QR factorization of sparse matrices on GPUs. Wrapper of the CUDA library cusolverSpDcsrqrsvBatched()
Home-page: UNKNOWN
Author: Giuseppe Romano
Author-email: romanog@mit.edu
License: GPLv2
Platform: UNKNOWN
Classifier: Programming Language :: Python :: 3.6
